LICENSE.md
README.md
setup.py
chess_gym/__init__.py
chess_gym.egg-info/PKG-INFO
chess_gym.egg-info/SOURCES.txt
chess_gym.egg-info/dependency_links.txt
chess_gym.egg-info/requires.txt
chess_gym.egg-info/top_level.txt
chess_gym/envs/__init__.py
chess_gym/envs/chess_env.py