Metadata-Version: 2.1
Name: chess-gym
Version: 0.0.5
Summary: OpenAI Gym environment for Chess, using the game engine of the python-chess module
Home-page: https://github.com/Ryan-Rudes/chess-gym
Author: Ryan Rudes
Author-email: ryanrudes@gmail.com
License: MIT License
License-File: LICENSE.md
